Metadata-Version: 2.1
Name: microcosm-flask2
Version: 4.0.0
Summary: Flask-based webserver micro framework (Flask 2.x Fork)
Home-page: https://github.com/globality-corp/microcosm-flask
Author: Globality Engineering
Author-email: engineering@globality.com
License: UNKNOWN
Keywords: microcosm
Platform: UNKNOWN
Requires-Python: >=3.6
Provides-Extra: metrics
Provides-Extra: profiling
Provides-Extra: sentry
Provides-Extra: spooky
Provides-Extra: test
Provides-Extra: lint
